gougleai.py
gougleai-1.0.5.5.dist-info/METADATA
gougleai-1.0.5.5.dist-info/WHEEL
gougleai-1.0.5.5.dist-info/top_level.txt
gougleai-1.0.5.5.dist-info/RECORD
