Metadata-Version: 2.1
Name: gougleai
Version: 1.0.5.5
Summary: The Python package for Gougle AI API.
Home-page: https://www.github.com/gougle-official/gougleai-python
Author: Gougle AI LLC
Author-email: gouglellc@gmail.com
License: GPL-2.0
Requires-Python: >=3.6
Requires-Dist: requests
